markyp_html/__init__.py
markyp_html/block.py
markyp_html/entities.py
markyp_html/forms.py
markyp_html/inline.py
markyp_html/lists.py
markyp_html/py.typed
markyp_html/tables.py
markyp_html/text.py
markyp_html-0.2306.2.dist-info/LICENSE
markyp_html-0.2306.2.dist-info/METADATA
markyp_html-0.2306.2.dist-info/WHEEL
markyp_html-0.2306.2.dist-info/top_level.txt
markyp_html-0.2306.2.dist-info/RECORD
