Metadata-Version: 2.1
Name: markyp-html
Version: 0.2306.2
Summary: HTML element implementations based on markyp.
Home-page: https://github.com/volfpeter/markyp-html
Author: Peter Volf
Author-email: do.volfp@gmail.com
License: MIT
Keywords: html markup generator utility
Classifier: Development Status :: 5 - Production/Stable
Classifier: Intended Audience :: Developers
Classifier: License :: OSI Approved :: MIT License
Classifier: Natural Language :: English
Classifier: Operating System :: OS Independent
Classifier: Programming Language :: Python :: 3 :: Only
Classifier: Programming Language :: Python :: 3.6
Classifier: Programming Language :: Python :: 3.7
Classifier: Programming Language :: Python :: 3.8
Classifier: Topic :: Internet :: WWW/HTTP :: Dynamic Content
Classifier: Topic :: Software Development :: Code Generators
Classifier: Topic :: Software Development :: Libraries :: Python Modules
Classifier: Topic :: Text Processing :: Markup :: HTML
Classifier: Topic :: Utilities
Classifier: Typing :: Typed
Requires-Python: >=3.6
License-File: LICENSE
Requires-Dist: markyp (>=0.2306)
